{
    "title": "Seven Deadly Sins",
    "main": [
        {
            "name": "lucemonfm",
            "line": "angemon"
        },
        {
            "name": "lilithmon",
            "line": "gatomon"
        },
        {
            "name": "barbamon",
            "line": "devimon"
        },
        {
            "name": "demon",
            "line": "impmon"
        },
        {
            "name": "beelzebumon",
            "line": "impmon"
        },
        {
            "name": "belphemonrm",
            "line": "phascomon"
        },
        {
            "name": "leviamon",
            "line": "seadramon"
        }
    ],
    "related": [
        {
            "name": "ogudomon"
        },
        {
            "name": "grandracmon",
            "line": "dracmon"
        },
        {
            "name": "gulfmon",
            "line": "phascomon"
        },
        {
            "name": "malomyotismon",
            "line": "devimon"
        }
    ]
}