{
    "columns": [
        [
            null,
            null,
            null,
            null,
            null,
            {
                "name": "chaosdramonx",
                "color": "x",
                "from": [
                    1,
                    0
                ]
            }
        ],
        [
            null,
            null,
            null,
            {
                "name": "hicommandramon",
                "from": [
                    1,
                    -1
                ]
            },
            {
                "name": "cargodramon"
            },
            {
                "name": "chaosdramon"
            }
        ],
        [
            {
                "name": "bommon"
            },
            {
                "name": "missimon"
            },
            {
                "name": "commandramon"
            },
            {
                "name": "sealsdramon"
            },
            {
                "name": "tankdramon",
                "from2": [
                    1,
                    -1
                ]
            },
            {
                "name": "darkdramon"
            },
            {
                "name": "chaosmon",
                "color": "fusion"
            },
            {
                "name": "ultimatechaosmon",
                "color": "fusion"
            }
        ],
        [
            null,
            null,
            null,
            {
                "name": "tankmon",
                "from": [
                    -1,
                    -1
                ]
            },
            {
                "name": "gundramon",
                "from": [
                    -1,
                    -1
                ]
            },
            null,
            null
        ],
        [
            null,
            null,
            null,
            {
                "name": "troopmon",
                "from": [
                    -2,
                    -1
                ]
            },
            {
                "name": "assaultmon"
            },
            {
                "name": "cannondramon"
            }
        ]
    ],
    "related": [
        {
            "name": "flarelizardmon",
            "for": "chaosdramon"
        },
        {
            "name": "gammamon",
            "for": "cannondramon"
        },
        {
            "name": "tyranomon",
            "for": "metaltyranomon"
        },
        {
            "name": "leomon",
            "for": "chaosmon"
        },
        {
            "name": "greymon",
            "for": "agumon"
        }
    ]
}