{"columns":[[null,null,null,{"name":"icedevimon","color":["ice"],"from":[[7,-1]]},{"name":"marinedevimon","color":["marine"],"from":[[0,-1]]},{"name":"cthyllamon","color":["marine"],"from":[[0,-1]]},null,null],[null,null,null,null,{"name":"ladydevimon_x","color":["x"],"from":[[1,0]]},{"name":"lilithmon_x","color":["x"],"from":[[0,-1]]},null,null],[null,null,null,null,{"name":"ladydevimon","color":["dark"],"from":[[2,-1]]},{"name":"lilithmon","color":["dark"],"from":[[0,-1]]},null,null],[null,null,null,null,null,{"name":"barbamon_x","from":[[1,0]],"color":["x"]},null,null],[null,null,null,{"name":"devidramon","from":[[3,-1]],"color":["dark"]},{"name":"skullsatamon","from":[[3,-1],[0,-1]],"color":["dark","dark"]},{"name":"barbamon","from":[[0,-1]],"color":["dark"]},null,null],[null,null,null,null,null,{"name":"demon_x","color":["x"],"from":[[1,0]]},null,null],[null,null,null,null,null,{"name":"demon","color":["dark","dark"],"skins":[],"from":[[1,-1],[-2,-1]]},null,{"name":"demon_super_ultimate","color":["fusion"],"from":[[0,-2]]}],[{"name":"zurumon","from":null},{"name":"pagumon","color":["dark"],"from":[[0,-1]]},{"name":"demidevimon","color":["dark"],"from":[[0,-1]]},{"name":"devimon","color":["dark"],"from":[[0,-1]]},{"name":"neodevimon","color":["dark"],"from":[[0,-1]]},{"name":"donedevimon","color":["dark"],"from":[[0,-1]]},null,null],[null,null,null,null,null,{"name":"neomyotismon","from":[[-1,-1],[1,-1]],"color":["dark","dark"]},{"name":"neomyotismon_darkness_mode","color":["dark"],"skins":["neomyotismon_darkness_mode_metal_greymon"],"from":[[0,-1]]},null],[null,null,null,{"name":"pipismon","color":["dark"],"from":[[-2,-1]]},{"name":"myotismon","color":["dark","dark"],"from":[[0,-1],[-2,-1]]},{"name":"venommyotismon","color":["dark"],"from":[[0,-1]]},null,null],[null,null,null,null,{"name":"myotismon_x","color":["x"],"from":[[-1,0]]},{"name":"malomyotismon","color":["dark"],"from":[[-1,-1]]},null,null],[null,null,null,null,null,{"name":"boltboutamon","from":[[-2,-1]],"color":["fusion"]},null,null],[null,null,null,null,{"name":"lucemon_falldown_mode","color":["fusion"],"from":[[-5,-1]]},{"name":"lucemon_larva","color":["mode"],"from":[[0,-1]]},{"name":"lucemon_satan_mode","color":["mode"],"from":[[0,-1]]},{"name":"ogudomon","color":["fusion"],"from":[[0,-1]]}],[null,null,null,null,null,{"name":"lucemon_x","color":["x"],"from":[[-1,-1]]},null,null]],"related":["ogudomon",{"name":"patamon","from":"lucemon_falldown_mode"},{"name":"gatomon","from":"ladydevimon"},{"name":"dracmon","from":"myotismon"},{"name":"app_hackmon","for":"app_docmon"},{"name":"toyagumon","for":"boltboutamon"},{"name":"jellymon","for":"marinedevimon"},{"name":"impmon","for":"boogiemon"},{"name":"bakemon","for":"piemon"},{"name":"arkadimon","from":"demon_super_ultimate"},{"name":"fujamon","for":"leviamon"}],"size":8}