{
    "columns": [
        [
            null,
            null,
            {
                "name": "gazimonx",
                "color": "x",
                "from": [1,0]
            }
        ],
        [
            {
                "name": "zurumon"
            },
            {
                "name": "pagumon",
                "color": "dark"
            },
            {
                "name": "gazimon",
                "color": "dark"
            },
            {
                "name": "duskmon",
                "color": "dark"
            },
            {
                "name": "velgrmon",
                "color": "dark"
            },
            {
                "name": "bagramon",
                "color": "dark"
            },
            {
                "name": "darkknightmonbagramon",
                "color": "fusion"
            },
            {
                "name": "darknessbagramon",
                "color": "fusion"
            }
        ]
    ],
    "related": [
        {
            "name": "pawnchessmonwhite",
            "for": "darkknightmon"
        },
        {
            "name": "garurumon",
            "for": "gaomon"
        }
    ]
}