{
    "columns": [
        [
            null,
            null,
            {
                "name": "gazimonx",
                "color": "x",
                "from": [
                    1,
                    0
                ]
            }
        ],
        [
            {
                "name": "zurumon"
            },
            {
                "name": "pagumon",
                "color": "dark"
            },
            {
                "name": "gazimon",
                "color": "dark"
            },
            {
                "name": "duskmon",
                "color": "dark"
            },
            {
                "name": "velgrmon",
                "color": "dark"
            },
            {
                "name": "bagramon",
                "color": "dark"
            },
            null,
            {
                "name": "darknessbagramon",
                "color": "fusion",
                "from": [
                    0,
                    2
                ]
            }
        ],
        [
            null,
            null,
            null,
            {
                "name": "ginkakumon",
                "from": [
                    -1,
                    -1
                ]
            }
        ],
        [
            null,
            null,
            null,
            {
                "name": "kinkakumon",
                "from": [
                    -2,
                    -1
                ]
            }
        ]
    ],
    "related": [
        {
            "name": "pawnchessmonwhite",
            "for": "darkknightmon"
        },
        {
            "name": "garurumon",
            "for": "gaomon"
        },
        {
            "name": "negamon",
            "for": "eyesmon"
        },
        "dracmon"
    ]
}