{
	"columns": [
		[
			null,
			null,
			{
				"name": "impmonx",
				"color": "x",
				"xSize": 2,
				"from": [2, 0],
				"xCollapsable": false,
				"yCollapsable": false
			},
			{
				"name": "wizardmonx",
				"color": "x",
				"xSize": 2,
				"xCollapsable": false,
				"yCollapsable": false
			},
			{
				"name": "baalmonx",
				"color": "x",
				"xSize": 2,
				"xCollapsable": false,
				"yCollapsable": false
			},
			{
				"name": "beelzebumonx",
				"color": "x",
				"from": [0.5, -1],
				"xCollapsable": false,
				"yCollapsable": true
			},
			null
		],
		[
			null,
			null,
			null,
			null,
			null,
			{
				"name": "beelstarmonx",
				"color": "x",
				"from": [-0.5, -1],
				"xCollapsable": false,
				"yCollapsable": false
			},
			{
				"name": "nezhamoncm",
				"from": [[0.5, -1]],
				"xCollapsable": false,
				"yCollapsable": true,
				"xSize": 2,
				"color": ["fusion"]
			}
		],
		[
			{
				"name": "keemon",
				"xSize": 2,
				"from": null,
				"xCollapsable": false,
				"yCollapsable": false
			},
			{
				"name": "yarmon",
				"color": "dark",
				"xSize": 2,
				"xCollapsable": false,
				"yCollapsable": false
			},
			{
				"name": "impmon",
				"color": "dark",
				"xSize": 2,
				"xCollapsable": false,
				"yCollapsable": false
			},
			{
				"name": "wizardmon",
				"xSize": 2,
				"xCollapsable": false,
				"yCollapsable": false
			},
			{
				"name": "deathmeramon",
				"xCollapsable": false,
				"yCollapsable": false,
				"from": [[0.5, -1]],
				"color": ["dark"]
			},
			{
				"color": ["dark"],
				"name": "beelzebumon",
				"from": [[0, -1]],
				"skins": ["beelzebumonbehemoth"],
				"xCollapsable": false,
				"yCollapsable": false
			},
			{
				"name": "beelzebumonbm",
				"color": "mode",
				"xCollapsable": false,
				"yCollapsable": true,
				"from": [[-0.5, -1]],
				"xSize": 2
			}
		],
		[
			null,
			null,
			null,
			null,
			{
				"name": "baalmon",
				"from": [[-0.5, -1]],
				"xCollapsable": true,
				"yCollapsable": false
			},
			{
				"name": "beelzebumon2",
				"color": ["dark"],
				"from": [[0, -1]],
				"xCollapsable": false,
				"yCollapsable": true
			},
			null
		],
		[
			null,
			null,
			{
				"name": "petitmamon",
				"from": [[-1.5, -1]],
				"xCollapsable": true,
				"yCollapsable": true,
				"color": ["dark"]
			},
			null,
			null,
			{
				"name": "beelstarmon",
				"from": [[-1, -1]],
				"xCollapsable": false,
				"yCollapsable": true,
				"color": ["dark"]
			},
			null
		],
		[
			null,
			null,
			null,
			{
				"name": "punkmon",
				"color": ["dark"],
				"from": [[-2.5, -1]],
				"xCollapsable": false,
				"yCollapsable": false
			},
			{
				"name": "loudmon",
				"color": "dark",
				"xCollapsable": false,
				"yCollapsable": false
			},
			{
				"name": "heavymetaldramon",
				"color": "dark",
				"xCollapsable": false,
				"yCollapsable": true
			},
			null
		],
		[
			null,
			null,
			null,
			{
				"name": "boogiemon",
				"color": ["dark"],
				"from": [[-3.5, -1]],
				"xCollapsable": true,
				"yCollapsable": false
			},
			{
				"name": "phelesmon",
				"color": "dark",
				"xCollapsable": true,
				"yCollapsable": false
			},
			{
				"name": "barbamon",
				"color": "dark",
				"xCollapsable": false,
				"yCollapsable": true
			},
			null
		],
		[
			null,
			null,
			null,
			null,
			null,
			{
				"name": "barbamonx",
				"color": "x",
				"from": [-1, 0],
				"xCollapsable": false,
				"yCollapsable": true
			},
			null
		]
	],
	"related": [
		"guilmon",
		"ogudomon",
		"wizardmon",
		{ "name": "meramon", "for": "deathmeramon" },
		{ "name": "devimon", "for": "skullsatamon" },
		{ "name": "shoutmon", "for": "shoutmonx4b" },
		{ "name": "machmon", "from": "nezhamon" },
		{ "name": "golemon", "from": "vulcanusmon" },
		{ "name": "kakamon", "for": "dijiangmon" },
		{ "name": "hookmon", "for": "magnakidmon" },
		{ "name": "bemmon", "for": "omegaarmamon" },
		{ "name": "gatomon", "for": "ladydevimon" },
		{ "name": "sistermonblanc", "for": "sistermonnoirawake" }
	],
	"notes": [
		"Astar is demon close to Beelzebub in the demonology but Astamon is already taken as an Ultimate/Perfect on Belphemon line."
	],
	"size": 7
}
