{
    "columns": [
        [
            null,
            null,
            {
                "name": "palmonx",
                "color": "x",
                "from": [
                    2,
                    0
                ]
            },
            {
                "name": "togemonx",
                "color": "x"
            },
            {
                "name": "lilimonx",
                "color": "x"
            },
            {
                "name": "rosemonx",
                "color": "x"
            }
        ],
        [
            null,
            null,
            null,
            {
                "name": "ponchomon",
                "color": "dark",
                "from": [
                    1,
                    -1
                ]
            },
            null,
            {
                "name": "bancholilimon",
                "from": [
                    1,
                    -1
                ]
            }
        ],
        [
            {
                "name": "nyokimon"
            },
            {
                "name": "tanemon"
            },
            {
                "name": "palmon"
            },
            {
                "name": "togemon"
            },
            {
                "name": "lilimon"
            },
            {
                "name": "rosemon"
            },
            {
                "name": "rosemonbm",
                "color": "mode"
            }
        ],
        [
            null,
            null,
            null,
            {
                "name": "kabukimon",
                "from": [
                    1,
                    -1
                ]
            },
            null,
            null,
            {
                "name": "rafflesimon",
                "from": null,
                "color": "fusion",
                "fusionFrom": [
                    [
                        -1,
                        -1
                    ],
                    [
                        1,
                        -1
                    ]
                ]
            }
        ],
        [
            {
                "name": "yuramon"
            },
            {
                "name": "budmon"
            },
            {
                "name": "lalamon"
            },
            {
                "name": "sunflowmon"
            },
            {
                "name": "lilamon"
            },
            {
                "name": "lotusmon"
            }
        ],
        [
            null,
            null,
            null,
            {
                "name": "vegimon",
                "from": [
                    1,
                    -1
                ]
            },
            {
                "name": "blossomon",
                "from2": [
                    -1,
                    -1
                ]
            },
            {
                "name": "ceresmon"
            }
        ],
        [
            {
                "name": "nyokimon"
            },
            {
                "name": "tanemon"
            },
            {
                "name": "alraumon"
            },
            {
                "name": "zassoumon"
            },
            {
                "name": "ajatarmon"
            },
            {
                "name": "hydramon"
            }
        ],
        [
            null,
            null,
            null,
            {
                "name": "vegimonred",
                "from": [
                    -1,
                    -1
                ]
            },
            {
                "name": "oleamon",
                "color": "dark"
            },
            null,
            {
                "name": "rafflesimoncorrupted",
                "color": "dark",
                "from": [
                    0,
                    -2
                ]
            }
        ],
        [
            null,
            {
                "name": "yokomon",
                "from": [
                    -2,
                    -1
                ]
            },
            {
                "name": "floramon"
            },
            {
                "name": "kiwimon"
            },
            {
                "name": "sirenmon"
            },
            {
                "name": "ceresmonbird"
            }
        ],
        [
            null,
            null,
            null,
            null,
            {
                "name": "delumon",
                "from": [
                    -1,
                    -1
                ]
            }
        ],
        [
            null,
            null,
            {
                "name": "pomumon",
                "from": [
                    -2,
                    -1
                ]
            },
            {
                "name": "parasaumon"
            },
            {
                "name": "tropiamon"
            },
            {
                "name": "bloomlordmon"
            }
        ]
    ],
    "related": [
        "woodmon"
    ]
}